piltesseract/__init__.py
piltesseract/_version.py
piltesseract/tesseractwrapper.py
piltesseract-1.0.2.dist-info/DESCRIPTION.rst
piltesseract-1.0.2.dist-info/METADATA
piltesseract-1.0.2.dist-info/RECORD
piltesseract-1.0.2.dist-info/WHEEL
piltesseract-1.0.2.dist-info/metadata.json
piltesseract-1.0.2.dist-info/top_level.txt
