Metadata-Version: 2.0
Name: piltesseract
Version: 1.0.2
Summary: Image-to-text Tesseract command line wrapper.
Home-page: https://github.com/Digirolamo/PILtesseract/
Author: Christopher Digirolamo
Author-email: chrisdigirolamo@gmail.com
License: MIT License
Download-URL: https://github.com/Digirolamo/PILtesseract
Platform: UNKNOWN
Classifier: Development Status :: 3 - Alpha
Classifier: Intended Audience :: Developers
Classifier: License :: OSI Approved :: MIT License
Classifier: Operating System :: OS Independent
Classifier: Programming Language :: Python
Classifier: Programming Language :: Python :: 2.7
Classifier: Programming Language :: Python :: 3
Requires-Dist: six (>=1.8.0)
